{
  "main": [
    {
      "name": "Solusi Kami",
      "url": "/solusi-kami"
    },
    {
      "name": "Join Mitra Sibayar",
      "url": "/join"
    },
    {
      "name": "Voucher Game",
      "url": "/#"
    },
    {
      "name": "Contact",
      "url": "/contact"
    }
  ],
  "footer": [
    {
      "menu": [
        {
          "text": "PT Digital Voucher Market Bersama",
          "url": "#"
        },
        {
          "text": "Email: info@sibayar.id",
          "url": "#"
        }
      ]
    }
  ]
}
